github_actions_docs/__init__.py
github_actions_docs/__main__.py
github_actions_docs/cli.py
github_actions_docs/config.py
github_actions_docs/errors.py
github_actions_docs/lib/generator.py
github_actions_docs/lib/git.py
github_actions_docs/lib/parser.py
github_actions_docs/lib/styler.py
github_actions_docs-0.2.4.dist-info/LICENSE
github_actions_docs-0.2.4.dist-info/METADATA
github_actions_docs-0.2.4.dist-info/WHEEL
github_actions_docs-0.2.4.dist-info/entry_points.txt
github_actions_docs-0.2.4.dist-info/top_level.txt
github_actions_docs-0.2.4.dist-info/RECORD
