Metadata-Version: 2.1
Name: github-actions-docs
Version: 0.2.4
Summary: Generate github actions documentation in markdown format.
Author-email: "Reza J. Bavaghoush" <rzjfr@yahoo.com>
Project-URL: Homepage, https://github.com/rzjfr/github-actions-docs
Classifier: Development Status :: 2 - Pre-Alpha
Classifier: Environment :: Console
Classifier: Intended Audience :: Developers
Classifier: Operating System :: OS Independent
Classifier: License :: OSI Approved :: MIT License
Classifier: Programming Language :: Python :: 3 :: Only
Classifier: Programming Language :: Python :: 3.10
Classifier: Programming Language :: Python :: 3.11
Classifier: Programming Language :: Python :: 3.12
Requires-Python: >=3.10
License-File: LICENSE
Requires-Dist: importlib-metadata >=6.8.0
Requires-Dist: ruamel.yaml <=0.18.0
Requires-Dist: pygments
